IndoEmotions/__init__.py
IndoEmotions/dataset.py
IndoEmotions-0.0.1.dist-info/METADATA
IndoEmotions-0.0.1.dist-info/WHEEL
IndoEmotions-0.0.1.dist-info/top_level.txt
IndoEmotions-0.0.1.dist-info/RECORD
