Metadata-Version: 2.1
Name: IndoEmotions
Version: 0.0.1
Summary: A benchmark data and model for emotion analysis from Indonesian based text
Home-page: https://github.com/gilangcy/IndoEmotions
Author: Example Author
Author-email: author@example.com
License: UNKNOWN
Platform: UNKNOWN
Classifier: Programming Language :: Python :: 3
Classifier: License :: OSI Approved :: MIT License
Classifier: Operating System :: OS Independent
